exoedge/__init__.py
exoedge/__version__.py
exoedge/channel.py
exoedge/config_applications.py
exoedge/config_io.py
exoedge/config_io_schema.yaml
exoedge/configs.py
exoedge/constants.py
exoedge/data_in.py
exoedge/data_queuing.py
exoedge/edged.py
exoedge/logger.py
exoedge/namespaces.py
exoedge/options_handler.py
exoedge/sources.py
exoedge/commands/__init__.py
exoedge/commands/go.py
test/__init__.py
test/bak_test_data_queuing.py
test/test_channel.py
test/test_config_files.py
test/test_configs.py
test/test_constructors.py
test/test_namespace.py
exoedge-22.8.5.dist-info/LICENSE
exoedge-22.8.5.dist-info/METADATA
exoedge-22.8.5.dist-info/WHEEL
exoedge-22.8.5.dist-info/entry_points.txt
exoedge-22.8.5.dist-info/top_level.txt
exoedge-22.8.5.dist-info/RECORD
