Metadata-Version: 2.1
Name: exoedge
Version: 22.8.5
Summary: ExoEdge is the Python library for interacting with Exosite's ExoSense Industrial IoT Solution.
Home-page: https://github.com/exosite/lib_exoedge_python
Author: Exosite LLC
Author-email: support@exosite.com
License: Apache 2.0
Keywords: murano exosite iot iiot gateway edge exoedge exosense
Platform: UNKNOWN
Classifier: Development Status :: 4 - Beta
Classifier: Programming Language :: Python :: 3.5
Classifier: Programming Language :: Python :: 3.6
Classifier: Programming Language :: Python :: 3.7
Classifier: Operating System :: POSIX :: Linux
Classifier: Operating System :: MacOS :: MacOS X
Classifier: Topic :: Internet
Classifier: Topic :: Software Development :: Embedded Systems
Classifier: Topic :: Software Development :: Libraries :: Python Modules
Classifier: Topic :: Scientific/Engineering :: Interface Engine/Protocol Translator
Classifier: Intended Audience :: Manufacturing
Classifier: Intended Audience :: Healthcare Industry
Classifier: Intended Audience :: Science/Research
Classifier: Intended Audience :: Telecommunications Industry
Classifier: License :: OSI Approved :: Apache Software License
Classifier: Natural Language :: English
Requires-Python: >=3
Requires-Dist: appdirs
Requires-Dist: docopt (>=0.6.2)
Requires-Dist: jsonschema (==3.2.0)
Requires-Dist: pureyaml
Requires-Dist: murano-client (>=19.5.8)
Requires-Dist: ruamel.yaml
Requires-Dist: six
Requires-Dist: urllib3 (==1.26.7)
